docs/conf.py
pystock/__init__.py
pystock/exceptions.py
pystock/fff.py
pystock/models.py
pystock/portfolio.py
pystock/style.py
pystock/utils.py
pystock/frontier/__init__.py
pystock/frontier/curve_fitting.py
pystock/frontier/frontier.py
pystock0-0.3.0.dist-info/METADATA
pystock0-0.3.0.dist-info/WHEEL
pystock0-0.3.0.dist-info/licenses/LICENSE
pystock0-0.3.0.dist-info/RECORD
