Metadata-Version: 2.1
Name: pystock0
Version: 0.3.0
Summary: A library for portfolio optimization
Project-URL: Homepage, https://github.com/Hari31416/pystock
Project-URL: repository, https://github.com/Hari31416/pystock
Project-URL: documentation, https://hari31416.github.io/pystock/
Author-email: Harikesh Kushwaha <harikeshkumar0926@gmail.com>
License: MIT License
License-File: LICENSE
Keywords: optimization,portfolio,stock
Classifier: License :: OSI Approved :: MIT License
Classifier: Programming Language :: Python
Classifier: Programming Language :: Python :: 3
Requires-Python: >=3.7
Requires-Dist: beautifulsoup4
Requires-Dist: numpy
Requires-Dist: pandas
Requires-Dist: requests
Requires-Dist: scipy
Requires-Dist: statsmodels
Requires-Dist: tabulate
Requires-Dist: tqdm
Provides-Extra: download
Requires-Dist: black; extra == 'download'
Requires-Dist: yfinance; extra == 'download'
